setup.cfg
setup.py
PyTransmit.egg-info/PKG-INFO
PyTransmit.egg-info/SOURCES.txt
PyTransmit.egg-info/dependency_links.txt
PyTransmit.egg-info/top_level.txt
pytransmit/__init__.py
pytransmit/ftp.py