Metadata-Version: 1.1
Name: PyTransmit
Version: 0.1
Summary: A flexible FTPClient library for python web development.
Home-page: http://pytransmit.readthedocs.org/en/latest/
Author: Ajay Kumar N
Author-email: contact@pypix.com
License: BSD
Download-URL: https: //github.com/ajkumar25/PyTransmit/tarball/0.1
Platform: UNKNOWN
Classifier: Development Status :: 5 - Production/Stable
Classifier: Environment :: Web Environment
Classifier: Intended Audience :: Developers
Classifier: License :: OSI Approved :: BSD License
Classifier: Operating System :: OS Independent
Classifier: Programming Language :: Python
Classifier: Programming Language :: Python :: 2.6
Classifier: Programming Language :: Python :: 2.7
Classifier: Programming Language :: Python :: 3
Classifier: Programming Language :: Python :: 3.2
Classifier: Programming Language :: Python :: 3.3
Classifier: Topic :: Internet :: WWW/HTTP :: Dynamic Content
Classifier: Topic :: Software Development :: Libraries :: Python Modules
